LICENSE
MANIFEST.in
README.md
setup.cfg
setup.py
versioneer.py
./.DS_Store
./.gitattributes
./CODE_OF_CONDUCT.md
./CONTRIBUTING.md
./Dockerfile
./LICENSE
./MANIFEST.in
./README.md
./portfolio_analytical_solution_studies.py
./portfolio_optimisation.py
./setup.cfg
./setup.py
./versioneer.py
./adannealing/__init__.py
./adannealing/_version.py
./adannealing/annealer.py
./adannealing/plotting.py
./adannealing.egg-info/PKG-INFO
./adannealing.egg-info/SOURCES.txt
./adannealing.egg-info/dependency_links.txt
./adannealing.egg-info/requires.txt
./adannealing.egg-info/top_level.txt
./profiling/.DS_Store
./profiling/PRICEACTION_adj_eur_isin_bloom.parquet
./profiling/__init__.py
./profiling/financial.py
./profiling/run_configs.json
./tests/__init__.py
./tests/conftest.py
./tests/test_adannealing.py
adannealing/__init__.py
adannealing/_version.py
adannealing/annealer.py
adannealing/plotting.py
adannealing.egg-info/PKG-INFO
adannealing.egg-info/SOURCES.txt
adannealing.egg-info/dependency_links.txt
adannealing.egg-info/requires.txt
adannealing.egg-info/top_level.txt
profiling/__init__.py
profiling/financial.py
tests/__init__.py
tests/conftest.py
tests/test_adannealing.py